monite_mcp/__init__.py
monite_mcp/__main__.py
monite_mcp/schemas.py
monite_mcp/settings.py
monite_mcp-0.1.1.dist-info/METADATA
monite_mcp-0.1.1.dist-info/WHEEL
monite_mcp-0.1.1.dist-info/entry_points.txt
monite_mcp-0.1.1.dist-info/licenses/LICENSE
monite_mcp-0.1.1.dist-info/RECORD
