Metadata-Version: 2.4
Name: monite-mcp
Version: 0.1.1
Summary: MCP server for Monite's AI features - enables AI agents to access financial data automation and insights for Monite platform users.
Project-URL: Source code, https://github.com/team-monite/monite-mcp
Author-email: Ivan Zakutnii <ivan.zakutnii@monite.com>
License-Expression: MIT
License-File: LICENSE
Keywords: agents,mcp,python
Classifier: License :: OSI Approved :: MIT License
Classifier: Operating System :: OS Independent
Classifier: Programming Language :: Python :: 3
Requires-Python: >=3.12
Requires-Dist: mcp[cli]>=1.7.1
Requires-Dist: pydantic>=2.11.4
